mcp_vector_search/__init__.py
mcp_vector_search/py.typed
mcp_vector_search/analysis/__init__.py
mcp_vector_search/analysis/dead_code.py
mcp_vector_search/analysis/dead_code_formatters.py
mcp_vector_search/analysis/debt.py
mcp_vector_search/analysis/entry_points.py
mcp_vector_search/analysis/interpretation.py
mcp_vector_search/analysis/metrics.py
mcp_vector_search/analysis/trends.py
mcp_vector_search/analysis/baseline/__init__.py
mcp_vector_search/analysis/baseline/comparator.py
mcp_vector_search/analysis/baseline/manager.py
mcp_vector_search/analysis/collectors/__init__.py
mcp_vector_search/analysis/collectors/base.py
mcp_vector_search/analysis/collectors/cohesion.py
mcp_vector_search/analysis/collectors/complexity.py
mcp_vector_search/analysis/collectors/coupling.py
mcp_vector_search/analysis/collectors/halstead.py
mcp_vector_search/analysis/collectors/smells.py
mcp_vector_search/analysis/reporters/__init__.py
mcp_vector_search/analysis/reporters/console.py
mcp_vector_search/analysis/reporters/markdown.py
mcp_vector_search/analysis/reporters/sarif.py
mcp_vector_search/analysis/storage/__init__.py
mcp_vector_search/analysis/storage/metrics_store.py
mcp_vector_search/analysis/storage/schema.py
mcp_vector_search/analysis/storage/trend_tracker.py
mcp_vector_search/analysis/visualizer/__init__.py
mcp_vector_search/analysis/visualizer/d3_data.py
mcp_vector_search/analysis/visualizer/exporter.py
mcp_vector_search/analysis/visualizer/html_report.py
mcp_vector_search/analysis/visualizer/schemas.py
mcp_vector_search/cli/__init__.py
mcp_vector_search/cli/didyoumean.py
mcp_vector_search/cli/export.py
mcp_vector_search/cli/history.py
mcp_vector_search/cli/interactive.py
mcp_vector_search/cli/main.py
mcp_vector_search/cli/output.py
mcp_vector_search/cli/suggestions.py
mcp_vector_search/cli/commands/__init__.py
mcp_vector_search/cli/commands/analyze.py
mcp_vector_search/cli/commands/auto_index.py
mcp_vector_search/cli/commands/chat.py
mcp_vector_search/cli/commands/config.py
mcp_vector_search-1.2.27.dist-info/METADATA
mcp_vector_search-1.2.27.dist-info/WHEEL
mcp_vector_search-1.2.27.dist-info/entry_points.txt
mcp_vector_search-1.2.27.dist-info/licenses/LICENSE
mcp_vector_search-1.2.27.dist-info/RECORD
