Metadata-Version: 2.4
Name: mcp-vector-search
Version: 1.2.27
Summary: CLI-first semantic code search with MCP integration and interactive D3.js visualization for exploring code relationships
Project-URL: Homepage, https://github.com/bobmatnyc/mcp-vector-search
Project-URL: Documentation, https://mcp-vector-search.readthedocs.io
Project-URL: Repository, https://github.com/bobmatnyc/mcp-vector-search
Project-URL: Bug Tracker, https://github.com/bobmatnyc/mcp-vector-search/issues
Author-email: Robert Matsuoka <bob@matsuoka.com>
License: MIT License
License-File: LICENSE
Keywords: code-graph,code-search,d3js,force-layout,interactive-graph,mcp,semantic-search,vector-database,visualization
Classifier: Development Status :: 3 - Alpha
Classifier: Intended Audience :: Developers
Classifier: License :: OSI Approved :: MIT License
Classifier: Programming Language :: Python :: 3.11
Classifier: Programming Language :: Python :: 3.12
Classifier: Topic :: Scientific/Engineering :: Visualization
Classifier: Topic :: Software Development :: Code Generators
Classifier: Topic :: Software Development :: Libraries :: Python Modules
Classifier: Topic :: Software Development :: Quality Assurance
Requires-Python: >=3.11
Requires-Dist: aiofiles>=23.0.0
Requires-Dist: authlib>=1.6.4
Requires-Dist: chromadb>=0.5.0
Requires-Dist: click-didyoumean>=0.3.0
Requires-Dist: fastapi>=0.104.0
Requires-Dist: httpx>=0.25.0
Requires-Dist: loguru>=0.7.0
Requires-Dist: mcp>=1.12.4
Requires-Dist: orjson>=3.9.0
Requires-Dist: packaging>=23.0
Requires-Dist: py-mcp-installer>=0.1.4
Requires-Dist: pydantic-settings>=2.1.0
Requires-Dist: pydantic>=2.5.0
Requires-Dist: rich>=13.0.0
Requires-Dist: sentence-transformers>=2.2.2
Requires-Dist: starlette>=0.49.1
Requires-Dist: tree-sitter-language-pack>=0.9.0
Requires-Dist: tree-sitter>=0.20.1
Requires-Dist: typer>=0.9.0
Requires-Dist: uvicorn>=0.24.0
Requires-Dist: watchdog>=3.0.0
